diamond_price_predictor_ml/__init__.py
diamond_price_predictor_ml/config.py
diamond_price_predictor_ml/data/make_dataset.py
diamond_price_predictor_ml/data/transformer.py
diamond_price_predictor_ml/features/build_features.py
diamond_price_predictor_ml/features/transformer.py
diamond_price_predictor_ml/modeling/__init__.py
diamond_price_predictor_ml/modeling/train_model.py
diamond_price_predictor_ml/visualisation/eda_plots.py
diamond_price_predictor_ml-0.0.1.dist-info/METADATA
diamond_price_predictor_ml-0.0.1.dist-info/WHEEL
diamond_price_predictor_ml-0.0.1.dist-info/RECORD
