Metadata-Version: 2.3
Name: diamond_price_predictor_ml
Version: 0.0.1
Summary: Diamond price predictor ML package
Author: Your Name
Requires-Python: >=3.11,<4.0
Classifier: Programming Language :: Python :: 3
Requires-Dist: databricks-sdk (>=0.67.0,<0.68.0)
Requires-Dist: ipython
Requires-Dist: jupyterlab
Requires-Dist: loguru
Requires-Dist: matplotlib
Requires-Dist: mkdocs
Requires-Dist: mlflow (>=3.3.2,<4.0.0)
Requires-Dist: notebook
Requires-Dist: numpy
Requires-Dist: pandas
Requires-Dist: pip
Requires-Dist: pydantic-settings (>=2.10.1,<3.0.0)
Requires-Dist: python-dotenv
Requires-Dist: ruff
Requires-Dist: scikit-learn
Requires-Dist: seaborn (>=0.13.2,<0.14.0)
Requires-Dist: statsmodels (>=0.14.5,<0.15.0)
Requires-Dist: tqdm
Requires-Dist: typer
